cellex/__init__.py
cellex/esobject.py
cellex/summarydata.py
cellex/metrics/__init__.py
cellex/metrics/det.py
cellex/metrics/ep.py
cellex/metrics/es_mu.py
cellex/metrics/es_sd.py
cellex/metrics/esw_star.py
cellex/metrics/ges.py
cellex/metrics/nsi.py
cellex/plotting/__init__.py
cellex/plotting/gene_profile.py
cellex/plotting/heatmap.py
cellex/plotting/n_es_genes.py
cellex/plotting/save_as_pdf.py
cellex/preprocessing/__init__.py
cellex/preprocessing/anova.py
cellex/preprocessing/log_normalize.py
cellex/preprocessing/remove_non_expressed.py
cellex/utils/__init__.py
cellex/utils/compute_pvalues.py
cellex/utils/parse_input.py
cellex/utils/mapping/__init__.py
cellex/utils/mapping/human_ens_to_human_symbol.py
cellex/utils/mapping/human_symbol_to_human_ens.py
cellex/utils/mapping/mouse_ens_to_human_ens.py
cellex/utils/mapping/mouse_symbol_to_mouse_ens.py
cellex/utils/mapping/maps/Homo_sapiens.GRCh38.ens_v90.ensembl2gene_name_version.txt.gz
cellex/utils/mapping/maps/Homo_sapiens.GRCh38.ens_v90.gene_name_version2ensembl.txt.gz
cellex/utils/mapping/maps/Mus_musculus.GRCm38.ens_v90.gene_name_version2ensembl.txt.gz
cellex/utils/mapping/maps/hsapiens_mmusculus_unique_orthologs.GRCh37.ens_v91.txt.gz
cellex/utils/mapping/maps/hsapiens_mmusculus_unique_orthologs.GRCh38.ens_v100.txt.gz
cellex-1.2.2.dist-info/LICENSE
cellex-1.2.2.dist-info/METADATA
cellex-1.2.2.dist-info/WHEEL
cellex-1.2.2.dist-info/top_level.txt
cellex-1.2.2.dist-info/RECORD
