Metadata-Version: 2.1
Name: cellex
Version: 1.2.2
Summary: Compute single-cell cell-type expression specificity
Home-page: https://github.com/perslab/CELLEX
Author: Tobias O. Stannius
Author-email: stannius@sund.ku.dk
License: UNKNOWN
Platform: UNKNOWN
License-File: LICENSE
Requires-Dist: setuptools (>=41.2.0)
Requires-Dist: setuptools-scm (>=3.3.3)
Requires-Dist: numpy (>=1.17.0)
Requires-Dist: scipy (>=1.3.1)
Requires-Dist: pandas (>=1.0.3)
Requires-Dist: h5py (>=2.9.0)
Requires-Dist: loompy (>=3.0.6)
Requires-Dist: adjustText (>=0.7.3)
Requires-Dist: plotnine (>=0.6.0)
